{
    "stage_name": "水火相容",
    "replacement_home": [
        {
            "location": [1, 4],
            "direction": "down"
        }
    ],
    "deploy_plan": [
        {
            "groups": ["投锋", "挡人先锋"],
            "location": [1, 4],
            "direction": "down"
        },
        {
            "groups": ["号角", "基石", "地面C", "挡人先锋", "投锋", "重装", "其他地面"],
            "location": [1, 5],
            "direction": "right"
        },
        {
            "groups": ["玛恩纳"],
            "location": [3, 5],
            "direction": "right"
        },
        {
            "groups": ["群奶", "单奶"],
            "location": [2, 5],
            "direction": "right"
        },
        {
            "groups": ["百嘉", "基石", "地面C", "重装", "其他地面"],
            "location": [3, 6],
            "direction": "right"
        },
        {
            "groups": ["高台C", "控制", "狙击", "术师", "召唤", "辅助", "其他高台"],
            "location": [4, 5],
            "direction": "right"
        },
        {
            "groups": ["高台C", "控制", "狙击", "术师", "召唤", "辅助", "其他高台"],
            "location": [5, 5],
            "direction": "right"
        },
        {
            "groups": ["刺客", "异德", "其他地面"],
            "location": [1, 1],
            "direction": "right"
        },
        {
            "groups": ["刺客", "异德", "其他地面"],
            "location": [5, 2],
            "direction": "right"
        }
    ]
}
